{
  "butterfly": [
    {
      "id": "1",
      "commonName": "Mariposa Ulises",
      "scientificName": "Papilio ulysses",
      "family": "Papilionidae",
      "region": "Australia",
      "specificLocation": "Queensland, Norte de Australia",
      "habitat": "Selvas tropicales húmedas",
      "wingspan": 10.5,
      "wingspanUnit": "cm",
      "description": "Mariposa de color azul eléctrico brillante con bordes negros. Endémica del norte de Australia y considerada una de las más bellas del continente.",
      "conservationStatus": "stable",
      "threatLevel": "preocupación menor",
      "population": "abundante",
      "flightSeason": [
        "octubre",
        "noviembre",
        "diciembre",
        "enero",
        "febrero",
        "marzo"
      ],
      "hostPlants": [
        "Melicope elleryana",
        "Euodia species"
      ],
      "nectarSources": [
        "Pentas",
        "Ixora",
        "Lantana"
      ],
      "behavior": "Vuela en el dosel superior, males territoriales",
      "coordinates": {
        "latitude": -16.2186,
        "longitude": 145.7781
      },
      "colorPrimary": "#0AB6F0",
      "tags": [
        "endémica",
        "tropical",
        "azul brillante",
        "turismo"
      ],
      "publicId": "swwjn3wlrrax40fczrn1"
    },
    {
      "id": "2",
      "commonName": "Mariposa Monarca",
      "scientificName": "Danaus plexippus",
      "family": "Nymphalidae",
      "region": "Australia",
      "specificLocation": "Sur y Este de Australia, Nueva Zelanda",
      "habitat": "Jardines, campos abiertos, praderas",
      "wingspan": 8.9,
      "wingspanUnit": "cm",
      "description": "Famosa por sus migraciones épicas y su distintivo color naranja con venas negras. Especie introducida en Oceanía desde América del Norte.",
      "conservationStatus": "vulnerable",
      "threatLevel": "Casi amenazada",
      "population": "en declive",
      "flightSeason": [
        "septiembre",
        "octubre",
        "noviembre",
        "diciembre",
        "enero",
        "febrero",
        "marzo",
        "abril"
      ],
      "hostPlants": [
        "Gomphocarpus physocarpus",
        "Asclepias species"
      ],
      "nectarSources": [
        "Buddleja",
        "Grevillea",
        "Pentas"
      ],
      "behavior": "Migradora de larga distancia, vuela en grupos",
      "coordinates": {
        "latitude": -33.8688,
        "longitude": 151.2093
      },
      "colorPrimary": "#FEA711",
      "tags": [
        "migratoria",
        "introducida",
        "naranja",
        "icónica"
      ],
      "publicId": "danaus-plexippus"
    },
    {
      "id": "3",
      "commonName": "Birdwing Dorada",
      "scientificName": "Ornithoptera priamus",
      "family": "Papilionidae",
      "region": "Australia",
      "specificLocation": "Queensland tropical, Islas Salomón",
      "habitat": "Bosques tropicales primarios",
      "wingspan": 16,
      "wingspanUnit": "cm",
      "description": "Una de las mariposas más grandes del mundo. Los machos tienen colores verde esmeralda y dorado vibrantes.",
      "conservationStatus": "stable",
      "threatLevel": "Preocupación menor",
      "population": "estable",
      "flightSeason": [
        "noviembre",
        "diciembre",
        "enero",
        "febrero",
        "marzo"
      ],
      "hostPlants": [
        "Aristolochia tagala",
        "Pararistolochia praevenosa"
      ],
      "nectarSources": [
        "Pentas",
        "Ixora",
        "Mussaenda"
      ],
      "behavior": "Vuela alto en el dosel, dimorfismo sexual marcado",
      "coordinates": {
        "latitude": -17.3667,
        "longitude": 145.7833
      },
      "colorPrimary": "#33E211",
      "tags": [
        "gigante",
        "verde esmeralda",
        "bosque primario",
        "espectacular"
      ],
      "publicId": "ornithoptera-priamus"
    }
  ]
}
  